neurone_tools/__init__.py
neurone_tools/main.py
neurone_tools-1.1.dist-info/LICENSE
neurone_tools-1.1.dist-info/METADATA
neurone_tools-1.1.dist-info/WHEEL
neurone_tools-1.1.dist-info/top_level.txt
neurone_tools-1.1.dist-info/RECORD
