Metadata-Version: 2.1
Name: neurone-tools
Version: 1.1
Summary: Binary file reader for NeurOne Tesla EEG data
Home-page: https://github.com/jkschluesener/pyneurone_tools
Author: Jan K. Schluesener
Author-email: code@jkschluesener.xyz
License: GPL
Classifier: Programming Language :: Python :: 3
Classifier: Operating System :: OS Independent
Requires-Python: >=3.7
License-File: LICENSE
Requires-Dist: numpy (>=1.2)
Requires-Dist: pandas (>=1.3.0)
Requires-Dist: xmltodict (>=0.1)
Requires-Dist: natsort (>=8.0)
